doc/__init__.py
doc/source/__init__.py
doc/source/conf.py
doc/source/_static/__init__.py
lib_Partage_BSS/__init__.py
lib_Partage_BSS/exceptions/BSSConnexionException.py
lib_Partage_BSS/exceptions/DomainException.py
lib_Partage_BSS/exceptions/NameException.py
lib_Partage_BSS/exceptions/NotFoundException.py
lib_Partage_BSS/exceptions/ServiceException.py
lib_Partage_BSS/exceptions/TmpServiceException.py
lib_Partage_BSS/exceptions/__init__.py
lib_Partage_BSS/models/Account.py
lib_Partage_BSS/models/COS.py
lib_Partage_BSS/models/GlobalModel.py
lib_Partage_BSS/models/Group.py
lib_Partage_BSS/models/Resource.py
lib_Partage_BSS/models/__init__.py
lib_Partage_BSS/services/AccountService.py
lib_Partage_BSS/services/BSSConnexionService.py
lib_Partage_BSS/services/COSService.py
lib_Partage_BSS/services/DomainService.py
lib_Partage_BSS/services/GlobalService.py
lib_Partage_BSS/services/GroupService.py
lib_Partage_BSS/services/PartageService.py
lib_Partage_BSS/services/ResourceService.py
lib_Partage_BSS/services/__init__.py
lib_Partage_BSS/utils/BSSRequest.py
lib_Partage_BSS/utils/CheckMethods.py
lib_Partage_BSS/utils/Log.py
lib_Partage_BSS/utils/__init__.py
lib_Partage_BSS_univ_rennes-2.3.5.data/scripts/cli-bss.py
test_integration/__init__.py
test_integration/lib_Partage_BSS/__init__.py
test_integration/lib_Partage_BSS/services/__init__.py
test_integration/lib_Partage_BSS/services/conftest.py
test_integration/lib_Partage_BSS/services/test_BSSConnexion.py
test_integration/lib_Partage_BSS/services/test_ServiceAccount.py
test_integration/lib_Partage_BSS/services/test_ServiceGLobal.py
test_integration/lib_Partage_BSS/services/test_ServiceGroup.py
test_integration/lib_Partage_BSS/services/test_ServiceResource.py
test_integration/lib_Partage_BSS/utils/__init__.py
test_unitaire/__init__.py
test_unitaire/lib_Partage_BSS/__init__.py
test_unitaire/lib_Partage_BSS/services/__init__.py
test_unitaire/lib_Partage_BSS/services/test_BSSConnexion.py
lib_Partage_BSS_univ_rennes-2.3.5.dist-info/LICENSE
lib_Partage_BSS_univ_rennes-2.3.5.dist-info/METADATA
lib_Partage_BSS_univ_rennes-2.3.5.dist-info/WHEEL
lib_Partage_BSS_univ_rennes-2.3.5.dist-info/top_level.txt
lib_Partage_BSS_univ_rennes-2.3.5.dist-info/RECORD
