Metadata-Version: 2.1
Name: lib-Partage-BSS-univ-rennes
Version: 2.3.5
Summary: Bibliothèque permettant l'interrogation de l'API BSS Partage de RENATER
Home-page: https://github.com/dsi-univ-rennes1/libPythonBssApi
Author: DSI Univ Rennes1
Author-email: 
License: UNKNOWN
Platform: UNKNOWN
Classifier: Programming Language :: Python :: 3
Classifier: License :: OSI Approved :: Apache Software License
Classifier: Operating System :: OS Independent
Classifier: Natural Language :: French
Requires-Python: >=3.5
Requires-Dist: xmljson
Requires-Dist: requests
Requires-Dist: wheel
